{
  "project_info": {
    "project_number": "393763766567",
    "firebase_url": "https://roommateshopping-2303b-default-rtdb.firebaseio.com",
    "project_id": "roommateshopping-2303b",
    "storage_bucket": "roommateshopping-2303b.appspot.com"
  },
  "client": [
    {
      "client_info": {
        "mobilesdk_app_id": "1:393763766567:android:421ce5db67362ec130a902",
        "android_client_info": {
          "package_name": "edu.uga.cs.roommateshopping"
        }
      },
      "oauth_client": [
        {
          "client_id": "393763766567-5m1rm2ps1vo027lvnftriae3410vdm67.apps.googleusercontent.com",
          "client_type": 3
        }
      ],
      "api_key": [
        {
          "current_key": "AIzaSyAw3MNOTnz05FElAMrFjsm4uJWsa56Hu50"
        }
      ],
      "services": {
        "appinvite_service": {
          "other_platform_oauth_client": [
            {
              "client_id": "393763766567-5m1rm2ps1vo027lvnftriae3410vdm67.apps.googleusercontent.com",
              "client_type": 3
            }
          ]
        }
      }
    }
  ],
  "configuration_version": "1"
}